{
    "start": 0,
    "end": 171.209932,
    "tiers": {
        "words": {
            "type": "interval",
            "entries": [
                [
                    0.0,
                    0.68,
                    "sought"
                ],
                [
                    0.68,
                    0.77,
                    "bite"
                ],
                [
                    0.77,
                    0.87,
                    "kite"
                ],
                [
                    0.87,
                    1.39,
                    "moat"
                ],
                [
                    1.54,
                    1.79,
                    "bot"
                ],
                [
                    1.79,
                    2.58,
                    "led"
                ],
                [
                    2.58,
                    2.83,
                    "lie"
                ],
                [
                    2.83,
                    2.95,
                    "bout"
                ],
                [
                    2.95,
                    3.05,
                    "should"
                ],
                [
                    3.05,
                    3.11,
                    "ought"
                ],
                [
                    3.11,
                    3.69,
                    "code"
                ],
                [
                    3.69,
                    3.93,
                    "pug"
                ],
                [
                    3.93,
                    4.08,
                    "dog"
                ],
                [
                    4.08,
                    9.24,
                    "fur"
                ],
                [
                    9.27,
                    9.53,
                    "got"
                ],
                [
                    9.53,
                    10.17,
                    "buy"
                ],
                [
                    10.17,
                    10.63,
                    "sought"
                ],
                [
                    10.63,
                    10.72,
                    "tate"
                ],
                [
                    10.72,
                    10.81,
                    "suck"
                ],
                [
                    10.81,
                    12.02,
                    "die"
                ],
                [
                    12.02,
                    17.13,
                    "loot"
                ],
                [
                    17.13,
                    18.2,
                    "booed"
                ],
                [
                    18.2,
                    18.32,
                    "soup"
                ],
                [
                    18.32,
                    18.84,
                    "kid"
                ],
                [
                    18.84,
                    19.21,
                    "might"
                ],
                [
                    19.21,
                    19.33,
                    "bot"
                ],
                [
                    19.33,
                    20.49,
                    "set"
                ],
                [
                    20.49,
                    21.46,
                    "cod"
                ],
                [
                    21.46,
                    21.78,
                    "seat"
                ],
                [
                    21.78,
                    23.41,
                    "lad"
                ],
                [
                    23.41,
                    24.07,
                    "bid"
                ],
                [
                    24.07,
                    26.55,
                    "soak"
                ],
                [
                    26.55,
                    26.7,
                    "pot"
                ],
                [
                    26.7,
                    26.81,
                    "dog"
                ],
                [
                    26.81,
                    29.67,
                    "led"
                ],
                [
                    29.67,
                    30.15,
                    "tight"
                ],
                [
                    30.15,
                    30.45,
                    "fight"
                ],
                [
                    30.45,
                    30.88,
                    "date"
                ],
                [
                    30.88,
                    31.07,
                    "beet"
                ],
                [
                    31.07,
                    31.93,
                    "lad"
                ],
                [
                    31.93,
                    32.3,
                    "cat"
                ],
                [
                    32.3,
                    33.78,
                    "hoot"
                ],
                [
                    33.78,
                    33.84,
                    "were"
                ],
                [
                    33.84,
                    34.26,
                    "but"
                ],
                [
                    34.26,
                    35.72,
                    "nut"
                ],
                [
                    35.72,
                    35.83,
                    "should"
                ],
                [
                    35.83,
                    35.96,
                    "bout"
                ],
                [
                    35.96,
                    40.04,
                    "laid"
                ],
                [
                    40.04,
                    40.16,
                    "sit"
                ],
                [
                    40.16,
                    40.79,
                    "dug"
                ],
                [
                    40.79,
                    41.66,
                    "moat"
                ],
                [
                    41.66,
                    41.97,
                    "could"
                ],
                [
                    41.97,
                    43.0,
                    "bit"
                ],
                [
                    43.0,
                    43.23,
                    "bead"
                ],
                [
                    43.23,
                    43.32,
                    "laid"
                ],
                [
                    43.32,
                    46.38,
                    "sad"
                ],
                [
                    46.38,
                    49.97,
                    "spur"
                ],
                [
                    50.15,
                    53.25,
                    "booed"
                ],
                [
                    53.25,
                    53.59,
                    "seed"
                ],
                [
                    53.59,
                    53.65,
                    "caught"
                ],
                [
                    53.65,
                    53.98,
                    "tight"
                ],
                [
                    53.98,
                    54.38,
                    "bite"
                ],
                [
                    54.38,
                    54.65,
                    "guy"
                ],
                [
                    54.65,
                    54.86,
                    "deed"
                ],
                [
                    54.86,
                    55.62,
                    "met"
                ],
                [
                    55.62,
                    55.94,
                    "sip"
                ],
                [
                    55.94,
                    57.64,
                    "mode"
                ],
                [
                    57.64,
                    57.73,
                    "kite"
                ],
                [
                    57.73,
                    58.84,
                    "book"
                ],
                [
                    58.84,
                    59.16,
                    "soup"
                ],
                [
                    59.16,
                    66.09,
                    "fur"
                ],
                [
                    66.09,
                    67.03,
                    "could"
                ],
                [
                    67.03,
                    67.16,
                    "peck"
                ],
                [
                    67.16,
                    67.48,
                    "pot"
                ],
                [
                    67.48,
                    69.21,
                    "guy"
                ],
                [
                    69.21,
                    69.59,
                    "bat"
                ],
                [
                    69.59,
                    69.7,
                    "paid"
                ],
                [
                    69.7,
                    71.44,
                    "nut"
                ],
                [
                    71.44,
                    72.42,
                    "loot"
                ],
                [
                    72.42,
                    72.69,
                    "met"
                ],
                [
                    72.69,
                    73.3,
                    "cow"
                ],
                [
                    73.3,
                    73.36,
                    "buy"
                ],
                [
                    73.36,
                    73.58,
                    "sigh"
                ],
                [
                    73.58,
                    77.8,
                    "sir"
                ],
                [
                    77.83,
                    86.31,
                    "spur"
                ],
                [
                    86.31,
                    86.74,
                    "paid"
                ],
                [
                    86.74,
                    87.26,
                    "die"
                ],
                [
                    87.26,
                    87.39,
                    "shout"
                ],
                [
                    87.39,
                    87.65,
                    "but"
                ],
                [
                    87.65,
                    89.44,
                    "pawn"
                ],
                [
                    89.44,
                    89.66,
                    "pout"
                ],
                [
                    89.66,
                    89.78,
                    "tate"
                ],
                [
                    89.78,
                    90.3,
                    "bid"
                ],
                [
                    90.3,
                    90.42,
                    "ought"
                ],
                [
                    90.42,
                    90.82,
                    "took"
                ],
                [
                    90.82,
                    93.59,
                    "mad"
                ],
                [
                    93.59,
                    104.89,
                    "dug"
                ],
                [
                    104.89,
                    105.24,
                    "cook"
                ],
                [
                    105.24,
                    107.08,
                    "shout"
                ],
                [
                    107.08,
                    108.45,
                    "soak"
                ],
                [
                    108.45,
                    108.54,
                    "beet"
                ],
                [
                    108.54,
                    110.48,
                    "bit"
                ],
                [
                    110.48,
                    115.41,
                    "bet"
                ],
                [
                    115.41,
                    116.14,
                    "bought"
                ],
                [
                    116.14,
                    127.38,
                    "bat"
                ],
                [
                    127.38,
                    127.47,
                    "fight"
                ],
                [
                    127.47,
                    127.83,
                    "cat"
                ],
                [
                    127.83,
                    128.39,
                    "peck"
                ],
                [
                    128.39,
                    128.64,
                    "deed"
                ],
                [
                    128.64,
                    132.53,
                    "cook"
                ],
                [
                    132.53,
                    132.59,
                    "lie"
                ],
                [
                    132.59,
                    132.83,
                    "sip"
                ],
                [
                    132.83,
                    132.92,
                    "pug"
                ],
                [
                    132.92,
                    134.64,
                    "her"
                ],
                [
                    134.64,
                    137.62,
                    "boot"
                ],
                [
                    137.65,
                    138.85,
                    "date"
                ],
                [
                    138.85,
                    139.23,
                    "pout"
                ],
                [
                    139.23,
                    140.79,
                    "were"
                ],
                [
                    141.01,
                    141.24,
                    "caught"
                ],
                [
                    141.24,
                    141.33,
                    "took"
                ],
                [
                    141.33,
                    142.06,
                    "kid"
                ],
                [
                    142.06,
                    142.18,
                    "seat"
                ],
                [
                    142.18,
                    142.75,
                    "book"
                ],
                [
                    142.75,
                    143.04,
                    "pouch"
                ],
                [
                    143.04,
                    144.18,
                    "boat"
                ],
                [
                    144.21,
                    144.58,
                    "set"
                ],
                [
                    144.58,
                    146.4,
                    "her"
                ],
                [
                    146.4,
                    146.69,
                    "boat"
                ],
                [
                    146.69,
                    146.75,
                    "sit"
                ],
                [
                    146.75,
                    149.87,
                    "mad"
                ],
                [
                    149.87,
                    150.21,
                    "bought"
                ],
                [
                    150.21,
                    150.49,
                    "bead"
                ],
                [
                    150.49,
                    150.92,
                    "hoot"
                ],
                [
                    150.92,
                    151.79,
                    "pouch"
                ],
                [
                    151.79,
                    151.93,
                    "cod"
                ],
                [
                    151.93,
                    152.32,
                    "cow"
                ],
                [
                    152.32,
                    152.39,
                    "sir"
                ],
                [
                    152.39,
                    155.47,
                    "boot"
                ],
                [
                    155.47,
                    155.88,
                    "might"
                ],
                [
                    155.88,
                    155.97,
                    "bait"
                ],
                [
                    155.97,
                    156.39,
                    "sad"
                ],
                [
                    156.39,
                    159.33,
                    "code"
                ],
                [
                    159.33,
                    159.56,
                    "seed"
                ],
                [
                    159.56,
                    160.03,
                    "pawn"
                ],
                [
                    160.03,
                    160.17,
                    "mode"
                ],
                [
                    160.17,
                    160.27,
                    "bait"
                ],
                [
                    160.27,
                    160.68,
                    "sigh"
                ],
                [
                    160.68,
                    161.32,
                    "bet"
                ],
                [
                    161.32,
                    161.39,
                    "suck"
                ],
                [
                    161.39,
                    171.209932,
                    "got"
                ]
            ]
        },
        "phones": {
            "type": "interval",
            "entries": [
                [
                    0.0,
                    0.03,
                    "S"
                ],
                [
                    0.03,
                    0.06,
                    "AA1"
                ],
                [
                    0.06,
                    0.68,
                    "T"
                ],
                [
                    0.68,
                    0.71,
                    "B"
                ],
                [
                    0.71,
                    0.74,
                    "AY1"
                ],
                [
                    0.74,
                    0.77,
                    "T"
                ],
                [
                    0.77,
                    0.8,
                    "K"
                ],
                [
                    0.8,
                    0.83,
                    "AY1"
                ],
                [
                    0.83,
                    0.87,
                    "T"
                ],
                [
                    0.87,
                    0.93,
                    "M"
                ],
                [
                    0.93,
                    1.34,
                    "OW1"
                ],
                [
                    1.34,
                    1.39,
                    "T"
                ],
                [
                    1.54,
                    1.57,
                    "B"
                ],
                [
                    1.57,
                    1.75,
                    "AA1"
                ],
                [
                    1.75,
                    1.79,
                    "T"
                ],
                [
                    1.79,
                    1.82,
                    "L"
                ],
                [
                    1.82,
                    1.86,
                    "EH1"
                ],
                [
                    1.86,
                    2.58,
                    "D"
                ],
                [
                    2.58,
                    2.63,
                    "L"
                ],
                [
                    2.63,
                    2.83,
                    "AY1"
                ],
                [
                    2.83,
                    2.86,
                    "B"
                ],
                [
                    2.86,
                    2.9,
                    "AW1"
                ],
                [
                    2.9,
                    2.95,
                    "T"
                ],
                [
                    2.95,
                    2.99,
                    "SH"
                ],
                [
                    2.99,
                    3.02,
                    "UH1"
                ],
                [
                    3.02,
                    3.05,
                    "D"
                ],
                [
                    3.05,
                    3.08,
                    "AA1"
                ],
                [
                    3.08,
                    3.11,
                    "T"
                ],
                [
                    3.11,
                    3.14,
                    "K"
                ],
                [
                    3.14,
                    3.21,
                    "OW1"
                ],
                [
                    3.21,
                    3.69,
                    "D"
                ],
                [
                    3.69,
                    3.72,
                    "P"
                ],
                [
                    3.72,
                    3.84,
                    "AH1"
                ],
                [
                    3.84,
                    3.93,
                    "G"
                ],
                [
                    3.93,
                    3.97,
                    "D"
                ],
                [
                    3.97,
                    4.0,
                    "AA1"
                ],
                [
                    4.0,
                    4.08,
                    "G"
                ],
                [
                    4.08,
                    4.11,
                    "F"
                ],
                [
                    4.11,
                    9.24,
                    "ER1"
                ],
                [
                    9.27,
                    9.3,
                    "G"
                ],
                [
                    9.3,
                    9.53,
                    "AA1"
                ],
                [
                    9.53,
                    10.14,
                    "B"
                ],
                [
                    10.14,
                    10.17,
                    "AY1"
                ],
                [
                    10.17,
                    10.35,
                    "S"
                ],
                [
                    10.35,
                    10.6,
                    "AO1"
                ],
                [
                    10.6,
                    10.63,
                    "T"
                ],
                [
                    10.63,
                    10.66,
                    "T"
                ],
                [
                    10.66,
                    10.69,
                    "EY1"
                ],
                [
                    10.69,
                    10.72,
                    "T"
                ],
                [
                    10.72,
                    10.75,
                    "S"
                ],
                [
                    10.75,
                    10.78,
                    "AH1"
                ],
                [
                    10.78,
                    10.81,
                    "K"
                ],
                [
                    10.81,
                    10.84,
                    "D"
                ],
                [
                    10.84,
                    12.02,
                    "AY1"
                ],
                [
                    12.02,
                    16.07,
                    "L"
                ],
                [
                    16.07,
                    16.99,
                    "UW1"
                ],
                [
                    16.99,
                    17.13,
                    "T"
                ],
                [
                    17.13,
                    17.17,
                    "B"
                ],
                [
                    17.17,
                    17.6,
                    "UW1"
                ],
                [
                    17.6,
                    18.2,
                    "D"
                ],
                [
                    18.2,
                    18.23,
                    "S"
                ],
                [
                    18.23,
                    18.29,
                    "UW1"
                ],
                [
                    18.29,
                    18.32,
                    "P"
                ],
                [
                    18.32,
                    18.35,
                    "K"
                ],
                [
                    18.35,
                    18.77,
                    "IH1"
                ],
                [
                    18.77,
                    18.84,
                    "D"
                ],
                [
                    18.84,
                    18.88,
                    "M"
                ],
                [
                    18.88,
                    19.21,
                    "AY1"
                ],
                [
                    19.21,
                    19.26,
                    "B"
                ],
                [
                    19.26,
                    19.29,
                    "AA1"
                ],
                [
                    19.29,
                    19.33,
                    "T"
                ],
                [
                    19.33,
                    19.51,
                    "S"
                ],
                [
                    19.51,
                    20.45,
                    "EH1"
                ],
                [
                    20.45,
                    20.49,
                    "T"
                ],
                [
                    20.49,
                    20.53,
                    "S"
                ],
                [
                    20.53,
                    20.79,
                    "IY1"
                ],
                [
                    20.79,
                    21.4,
                    "OW1"
                ],
                [
                    21.4,
                    21.43,
                    "D"
                ],
                [
                    21.43,
                    21.46,
                    "IY1"
                ],
                [
                    21.46,
                    21.6,
                    "S"
                ],
                [
                    21.6,
                    21.78,
                    "IY1"
                ],
                [
                    21.78,
                    22.57,
                    "L"
                ],
                [
                    22.57,
                    23.34,
                    "AE1"
                ],
                [
                    23.34,
                    23.41,
                    "D"
                ],
                [
                    23.41,
                    23.44,
                    "B"
                ],
                [
                    23.44,
                    24.02,
                    "IH1"
                ],
                [
                    24.02,
                    24.07,
                    "D"
                ],
                [
                    24.07,
                    24.13,
                    "S"
                ],
                [
                    24.13,
                    26.52,
                    "OW1"
                ],
                [
                    26.52,
                    26.55,
                    "K"
                ],
                [
                    26.55,
                    26.58,
                    "P"
                ],
                [
                    26.58,
                    26.67,
                    "AA1"
                ],
                [
                    26.67,
                    26.7,
                    "T"
                ],
                [
                    26.7,
                    26.73,
                    "D"
                ],
                [
                    26.73,
                    26.78,
                    "AA1"
                ],
                [
                    26.78,
                    26.81,
                    "G"
                ],
                [
                    26.81,
                    26.84,
                    "L"
                ],
                [
                    26.84,
                    29.54,
                    "EH1"
                ],
                [
                    29.54,
                    29.67,
                    "D"
                ],
                [
                    29.67,
                    29.7,
                    "T"
                ],
                [
                    29.7,
                    30.15,
                    "AY1"
                ],
                [
                    30.15,
                    30.19,
                    "F"
                ],
                [
                    30.19,
                    30.39,
                    "AY1"
                ],
                [
                    30.39,
                    30.45,
                    "T"
                ],
                [
                    30.45,
                    30.48,
                    "D"
                ],
                [
                    30.48,
                    30.85,
                    "EY1"
                ],
                [
                    30.85,
                    30.88,
                    "T"
                ],
                [
                    30.88,
                    30.91,
                    "B"
                ],
                [
                    30.91,
                    31.03,
                    "IY1"
                ],
                [
                    31.03,
                    31.07,
                    "T"
                ],
                [
                    31.07,
                    31.13,
                    "L"
                ],
                [
                    31.13,
                    31.88,
                    "AE1"
                ],
                [
                    31.88,
                    31.93,
                    "D"
                ],
                [
                    31.93,
                    31.98,
                    "K"
                ],
                [
                    31.98,
                    32.27,
                    "AE1"
                ],
                [
                    32.27,
                    32.3,
                    "T"
                ],
                [
                    32.3,
                    33.72,
                    "HH"
                ],
                [
                    33.72,
                    33.75,
                    "UW1"
                ],
                [
                    33.75,
                    33.78,
                    "T"
                ],
                [
                    33.78,
                    33.81,
                    "W"
                ],
                [
                    33.81,
                    33.84,
                    "ER0"
                ],
                [
                    33.84,
                    33.87,
                    "B"
                ],
                [
                    33.87,
                    34.22,
                    "AH1"
                ],
                [
                    34.22,
                    34.26,
                    "T"
                ],
                [
                    34.26,
                    34.29,
                    "N"
                ],
                [
                    34.29,
                    35.69,
                    "AH1"
                ],
                [
                    35.69,
                    35.72,
                    "T"
                ],
                [
                    35.72,
                    35.8,
                    "SH"
                ],
                [
                    35.8,
                    35.83,
                    "UH1"
                ],
                [
                    35.83,
                    35.86,
                    "B"
                ],
                [
                    35.86,
                    35.96,
                    "AW1"
                ],
                [
                    35.96,
                    39.82,
                    "L"
                ],
                [
                    39.82,
                    39.97,
                    "EY1"
                ],
                [
                    39.97,
                    40.04,
                    "D"
                ],
                [
                    40.04,
                    40.07,
                    "S"
                ],
                [
                    40.07,
                    40.13,
                    "IH1"
                ],
                [
                    40.13,
                    40.16,
                    "T"
                ],
                [
                    40.16,
                    40.19,
                    "D"
                ],
                [
                    40.19,
                    40.66,
                    "AH1"
                ],
                [
                    40.66,
                    40.79,
                    "G"
                ],
                [
                    40.79,
                    40.82,
                    "M"
                ],
                [
                    40.82,
                    41.63,
                    "OW1"
                ],
                [
                    41.63,
                    41.66,
                    "T"
                ],
                [
                    41.66,
                    41.69,
                    "K"
                ],
                [
                    41.69,
                    41.93,
                    "UH1"
                ],
                [
                    41.93,
                    41.97,
                    "D"
                ],
                [
                    41.97,
                    42.01,
                    "B"
                ],
                [
                    42.01,
                    42.95,
                    "IH1"
                ],
                [
                    42.95,
                    43.0,
                    "T"
                ],
                [
                    43.0,
                    43.04,
                    "B"
                ],
                [
                    43.04,
                    43.2,
                    "IY1"
                ],
                [
                    43.2,
                    43.23,
                    "D"
                ],
                [
                    43.23,
                    43.26,
                    "L"
                ],
                [
                    43.26,
                    43.29,
                    "EY1"
                ],
                [
                    43.29,
                    43.32,
                    "D"
                ],
                [
                    43.32,
                    43.35,
                    "S"
                ],
                [
                    43.35,
                    46.33,
                    "AE1"
                ],
                [
                    46.33,
                    46.38,
                    "D"
                ],
                [
                    46.38,
                    46.43,
                    "S"
                ],
                [
                    46.43,
                    46.46,
                    "P"
                ],
                [
                    46.46,
                    49.97,
                    "ER1"
                ],
                [
                    50.15,
                    50.18,
                    "B"
                ],
                [
                    50.18,
                    53.17,
                    "UW1"
                ],
                [
                    53.17,
                    53.25,
                    "D"
                ],
                [
                    53.25,
                    53.41,
                    "S"
                ],
                [
                    53.41,
                    53.56,
                    "IY1"
                ],
                [
                    53.56,
                    53.59,
                    "D"
                ],
                [
                    53.59,
                    53.62,
                    "K"
                ],
                [
                    53.62,
                    53.65,
                    "AA1"
                ],
                [
                    53.65,
                    53.69,
                    "T"
                ],
                [
                    53.69,
                    53.98,
                    "AY1"
                ],
                [
                    53.98,
                    54.12,
                    "B"
                ],
                [
                    54.12,
                    54.16,
                    "AY1"
                ],
                [
                    54.16,
                    54.38,
                    "T"
                ],
                [
                    54.38,
                    54.43,
                    "G"
                ],
                [
                    54.43,
                    54.65,
                    "AY1"
                ],
                [
                    54.65,
                    54.75,
                    "D"
                ],
                [
                    54.75,
                    54.86,
                    "IY1"
                ],
                [
                    54.86,
                    55.56,
                    "M"
                ],
                [
                    55.56,
                    55.59,
                    "EH1"
                ],
                [
                    55.59,
                    55.62,
                    "T"
                ],
                [
                    55.62,
                    55.65,
                    "S"
                ],
                [
                    55.65,
                    55.91,
                    "IH1"
                ],
                [
                    55.91,
                    55.94,
                    "P"
                ],
                [
                    55.94,
                    55.97,
                    "M"
                ],
                [
                    55.97,
                    57.61,
                    "OW1"
                ],
                [
                    57.61,
                    57.64,
                    "D"
                ],
                [
                    57.64,
                    57.67,
                    "K"
                ],
                [
                    57.67,
                    57.7,
                    "AY1"
                ],
                [
                    57.7,
                    57.73,
                    "T"
                ],
                [
                    57.73,
                    57.76,
                    "B"
                ],
                [
                    57.76,
                    58.81,
                    "UH1"
                ],
                [
                    58.81,
                    58.84,
                    "K"
                ],
                [
                    58.84,
                    58.87,
                    "S"
                ],
                [
                    58.87,
                    59.12,
                    "UW1"
                ],
                [
                    59.12,
                    59.16,
                    "P"
                ],
                [
                    59.16,
                    59.19,
                    "F"
                ],
                [
                    59.19,
                    66.09,
                    "ER1"
                ],
                [
                    66.09,
                    66.12,
                    "K"
                ],
                [
                    66.12,
                    67.0,
                    "UH1"
                ],
                [
                    67.0,
                    67.03,
                    "D"
                ],
                [
                    67.03,
                    67.06,
                    "P"
                ],
                [
                    67.06,
                    67.13,
                    "EH1"
                ],
                [
                    67.13,
                    67.16,
                    "K"
                ],
                [
                    67.16,
                    67.19,
                    "P"
                ],
                [
                    67.19,
                    67.45,
                    "AA1"
                ],
                [
                    67.45,
                    67.48,
                    "T"
                ],
                [
                    67.48,
                    67.51,
                    "G"
                ],
                [
                    67.51,
                    69.21,
                    "AY1"
                ],
                [
                    69.21,
                    69.33,
                    "B"
                ],
                [
                    69.33,
                    69.56,
                    "AE1"
                ],
                [
                    69.56,
                    69.59,
                    "T"
                ],
                [
                    69.59,
                    69.62,
                    "P"
                ],
                [
                    69.62,
                    69.67,
                    "EY1"
                ],
                [
                    69.67,
                    69.7,
                    "D"
                ],
                [
                    69.7,
                    69.75,
                    "N"
                ],
                [
                    69.75,
                    71.4,
                    "AH1"
                ],
                [
                    71.4,
                    71.44,
                    "T"
                ],
                [
                    71.44,
                    71.47,
                    "L"
                ],
                [
                    71.47,
                    72.39,
                    "UW1"
                ],
                [
                    72.39,
                    72.42,
                    "T"
                ],
                [
                    72.42,
                    72.51,
                    "M"
                ],
                [
                    72.51,
                    72.66,
                    "EH1"
                ],
                [
                    72.66,
                    72.69,
                    "T"
                ],
                [
                    72.69,
                    72.72,
                    "K"
                ],
                [
                    72.72,
                    73.3,
                    "AW1"
                ],
                [
                    73.3,
                    73.33,
                    "B"
                ],
                [
                    73.33,
                    73.36,
                    "AY1"
                ],
                [
                    73.36,
                    73.55,
                    "S"
                ],
                [
                    73.55,
                    73.58,
                    "AY1"
                ],
                [
                    73.58,
                    73.61,
                    "S"
                ],
                [
                    73.61,
                    77.8,
                    "ER1"
                ],
                [
                    77.83,
                    78.0,
                    "S"
                ],
                [
                    78.0,
                    78.03,
                    "P"
                ],
                [
                    78.03,
                    86.31,
                    "ER1"
                ],
                [
                    86.31,
                    86.41,
                    "P"
                ],
                [
                    86.41,
                    86.71,
                    "EY1"
                ],
                [
                    86.71,
                    86.74,
                    "D"
                ],
                [
                    86.74,
                    86.77,
                    "D"
                ],
                [
                    86.77,
                    87.26,
                    "AY1"
                ],
                [
                    87.26,
                    87.29,
                    "SH"
                ],
                [
                    87.29,
                    87.36,
                    "AW1"
                ],
                [
                    87.36,
                    87.39,
                    "T"
                ],
                [
                    87.39,
                    87.42,
                    "B"
                ],
                [
                    87.42,
                    87.59,
                    "AH1"
                ],
                [
                    87.59,
                    87.65,
                    "T"
                ],
                [
                    87.65,
                    87.68,
                    "P"
                ],
                [
                    87.68,
                    87.71,
                    "AO1"
                ],
                [
                    87.71,
                    89.44,
                    "N"
                ],
                [
                    89.44,
                    89.47,
                    "P"
                ],
                [
                    89.47,
                    89.62,
                    "AW1"
                ],
                [
                    89.62,
                    89.66,
                    "T"
                ],
                [
                    89.66,
                    89.69,
                    "T"
                ],
                [
                    89.69,
                    89.74,
                    "EY1"
                ],
                [
                    89.74,
                    89.78,
                    "T"
                ],
                [
                    89.78,
                    89.81,
                    "B"
                ],
                [
                    89.81,
                    90.15,
                    "IH1"
                ],
                [
                    90.15,
                    90.3,
                    "D"
                ],
                [
                    90.3,
                    90.39,
                    "AA1"
                ],
                [
                    90.39,
                    90.42,
                    "T"
                ],
                [
                    90.42,
                    90.47,
                    "T"
                ],
                [
                    90.47,
                    90.79,
                    "UH1"
                ],
                [
                    90.79,
                    90.82,
                    "K"
                ],
                [
                    90.82,
                    90.85,
                    "M"
                ],
                [
                    90.85,
                    93.56,
                    "AE1"
                ],
                [
                    93.56,
                    93.59,
                    "D"
                ],
                [
                    93.59,
                    93.62,
                    "D"
                ],
                [
                    93.62,
                    104.82,
                    "AH1"
                ],
                [
                    104.82,
                    104.89,
                    "G"
                ],
                [
                    104.89,
                    104.94,
                    "K"
                ],
                [
                    104.94,
                    105.21,
                    "UH1"
                ],
                [
                    105.21,
                    105.24,
                    "K"
                ],
                [
                    105.24,
                    105.31,
                    "SH"
                ],
                [
                    105.31,
                    107.05,
                    "AW1"
                ],
                [
                    107.05,
                    107.08,
                    "T"
                ],
                [
                    107.08,
                    107.11,
                    "S"
                ],
                [
                    107.11,
                    108.42,
                    "OW1"
                ],
                [
                    108.42,
                    108.45,
                    "K"
                ],
                [
                    108.45,
                    108.48,
                    "B"
                ],
                [
                    108.48,
                    108.51,
                    "IY1"
                ],
                [
                    108.51,
                    108.54,
                    "T"
                ],
                [
                    108.54,
                    108.58,
                    "B"
                ],
                [
                    108.58,
                    110.48,
                    "IH1"
                ],
                [
                    110.48,
                    111.93,
                    "B"
                ],
                [
                    111.93,
                    115.38,
                    "EH1"
                ],
                [
                    115.38,
                    115.41,
                    "T"
                ],
                [
                    115.41,
                    115.44,
                    "B"
                ],
                [
                    115.44,
                    116.11,
                    "AO1"
                ],
                [
                    116.11,
                    116.14,
                    "T"
                ],
                [
                    116.14,
                    116.17,
                    "B"
                ],
                [
                    116.17,
                    127.35,
                    "AE1"
                ],
                [
                    127.35,
                    127.38,
                    "T"
                ],
                [
                    127.38,
                    127.41,
                    "F"
                ],
                [
                    127.41,
                    127.44,
                    "AY1"
                ],
                [
                    127.44,
                    127.47,
                    "T"
                ],
                [
                    127.47,
                    127.5,
                    "K"
                ],
                [
                    127.5,
                    127.8,
                    "AE1"
                ],
                [
                    127.8,
                    127.83,
                    "T"
                ],
                [
                    127.83,
                    127.86,
                    "P"
                ],
                [
                    127.86,
                    128.36,
                    "EH1"
                ],
                [
                    128.36,
                    128.39,
                    "K"
                ],
                [
                    128.39,
                    128.43,
                    "D"
                ],
                [
                    128.43,
                    128.61,
                    "IY1"
                ],
                [
                    128.61,
                    128.64,
                    "D"
                ],
                [
                    128.64,
                    128.67,
                    "K"
                ],
                [
                    128.67,
                    132.5,
                    "UH1"
                ],
                [
                    132.5,
                    132.53,
                    "K"
                ],
                [
                    132.53,
                    132.56,
                    "L"
                ],
                [
                    132.56,
                    132.59,
                    "AY1"
                ],
                [
                    132.59,
                    132.62,
                    "S"
                ],
                [
                    132.62,
                    132.8,
                    "IH1"
                ],
                [
                    132.8,
                    132.83,
                    "P"
                ],
                [
                    132.83,
                    132.86,
                    "P"
                ],
                [
                    132.86,
                    132.89,
                    "AH1"
                ],
                [
                    132.89,
                    132.92,
                    "G"
                ],
                [
                    132.92,
                    132.95,
                    "HH"
                ],
                [
                    132.95,
                    134.64,
                    "ER1"
                ],
                [
                    134.64,
                    134.67,
                    "B"
                ],
                [
                    134.67,
                    137.62,
                    "UW1"
                ],
                [
                    137.65,
                    137.68,
                    "D"
                ],
                [
                    137.68,
                    138.82,
                    "EY1"
                ],
                [
                    138.82,
                    138.85,
                    "T"
                ],
                [
                    138.85,
                    138.88,
                    "P"
                ],
                [
                    138.88,
                    139.17,
                    "AW1"
                ],
                [
                    139.17,
                    139.23,
                    "T"
                ],
                [
                    139.23,
                    139.26,
                    "W"
                ],
                [
                    139.26,
                    140.79,
                    "ER1"
                ],
                [
                    141.01,
                    141.04,
                    "K"
                ],
                [
                    141.04,
                    141.2,
                    "AA1"
                ],
                [
                    141.2,
                    141.24,
                    "T"
                ],
                [
                    141.24,
                    141.27,
                    "T"
                ],
                [
                    141.27,
                    141.3,
                    "UH1"
                ],
                [
                    141.3,
                    141.33,
                    "K"
                ],
                [
                    141.33,
                    141.36,
                    "K"
                ],
                [
                    141.36,
                    141.83,
                    "IH1"
                ],
                [
                    141.83,
                    142.06,
                    "D"
                ],
                [
                    142.06,
                    142.09,
                    "S"
                ],
                [
                    142.09,
                    142.15,
                    "IY1"
                ],
                [
                    142.15,
                    142.18,
                    "T"
                ],
                [
                    142.18,
                    142.21,
                    "B"
                ],
                [
                    142.21,
                    142.72,
                    "UH1"
                ],
                [
                    142.72,
                    142.75,
                    "K"
                ],
                [
                    142.75,
                    142.78,
                    "P"
                ],
                [
                    142.78,
                    143.01,
                    "AW1"
                ],
                [
                    143.01,
                    143.04,
                    "CH"
                ],
                [
                    143.04,
                    143.07,
                    "B"
                ],
                [
                    143.07,
                    144.18,
                    "OW1"
                ],
                [
                    144.21,
                    144.39,
                    "S"
                ],
                [
                    144.39,
                    144.55,
                    "EH1"
                ],
                [
                    144.55,
                    144.58,
                    "T"
                ],
                [
                    144.58,
                    144.61,
                    "HH"
                ],
                [
                    144.61,
                    146.4,
                    "ER1"
                ],
                [
                    146.4,
                    146.45,
                    "B"
                ],
                [
                    146.45,
                    146.66,
                    "OW1"
                ],
                [
                    146.66,
                    146.69,
                    "T"
                ],
                [
                    146.69,
                    146.72,
                    "S"
                ],
                [
                    146.72,
                    146.75,
                    "IH1"
                ],
                [
                    146.75,
                    147.83,
                    "M"
                ],
                [
                    147.83,
                    149.84,
                    "AE1"
                ],
                [
                    149.84,
                    149.87,
                    "D"
                ],
                [
                    149.87,
                    149.9,
                    "B"
                ],
                [
                    149.9,
                    150.13,
                    "AA1"
                ],
                [
                    150.13,
                    150.21,
                    "T"
                ],
                [
                    150.21,
                    150.24,
                    "B"
                ],
                [
                    150.24,
                    150.46,
                    "IY1"
                ],
                [
                    150.46,
                    150.49,
                    "D"
                ],
                [
                    150.49,
                    150.52,
                    "HH"
                ],
                [
                    150.52,
                    150.89,
                    "UW1"
                ],
                [
                    150.89,
                    150.92,
                    "T"
                ],
                [
                    150.92,
                    150.96,
                    "P"
                ],
                [
                    150.96,
                    151.76,
                    "AW1"
                ],
                [
                    151.76,
                    151.79,
                    "CH"
                ],
                [
                    151.79,
                    151.82,
                    "K"
                ],
                [
                    151.82,
                    151.89,
                    "AA1"
                ],
                [
                    151.89,
                    151.93,
                    "D"
                ],
                [
                    151.93,
                    152.02,
                    "K"
                ],
                [
                    152.02,
                    152.32,
                    "AW1"
                ],
                [
                    152.32,
                    152.35,
                    "S"
                ],
                [
                    152.35,
                    152.39,
                    "ER1"
                ],
                [
                    152.39,
                    152.42,
                    "B"
                ],
                [
                    152.42,
                    155.47,
                    "UW1"
                ],
                [
                    155.47,
                    155.8,
                    "M"
                ],
                [
                    155.8,
                    155.85,
                    "AY1"
                ],
                [
                    155.85,
                    155.88,
                    "T"
                ],
                [
                    155.88,
                    155.91,
                    "B"
                ],
                [
                    155.91,
                    155.94,
                    "EY1"
                ],
                [
                    155.94,
                    155.97,
                    "T"
                ],
                [
                    155.97,
                    156.17,
                    "S"
                ],
                [
                    156.17,
                    156.36,
                    "AE1"
                ],
                [
                    156.36,
                    156.39,
                    "D"
                ],
                [
                    156.39,
                    156.42,
                    "K"
                ],
                [
                    156.42,
                    159.3,
                    "OW1"
                ],
                [
                    159.3,
                    159.33,
                    "D"
                ],
                [
                    159.33,
                    159.36,
                    "S"
                ],
                [
                    159.36,
                    159.53,
                    "IY1"
                ],
                [
                    159.53,
                    159.56,
                    "D"
                ],
                [
                    159.56,
                    159.59,
                    "P"
                ],
                [
                    159.59,
                    159.62,
                    "AA1"
                ],
                [
                    159.62,
                    160.03,
                    "N"
                ],
                [
                    160.03,
                    160.06,
                    "M"
                ],
                [
                    160.06,
                    160.1,
                    "OW1"
                ],
                [
                    160.1,
                    160.17,
                    "D"
                ],
                [
                    160.17,
                    160.2,
                    "B"
                ],
                [
                    160.2,
                    160.23,
                    "EY1"
                ],
                [
                    160.23,
                    160.27,
                    "T"
                ],
                [
                    160.27,
                    160.4,
                    "S"
                ],
                [
                    160.4,
                    160.68,
                    "AY1"
                ],
                [
                    160.68,
                    160.73,
                    "B"
                ],
                [
                    160.73,
                    161.29,
                    "EH1"
                ],
                [
                    161.29,
                    161.32,
                    "T"
                ],
                [
                    161.32,
                    161.33,
                    "S"
                ],
                [
                    161.33,
                    161.36,
                    "AH1"
                ],
                [
                    161.36,
                    161.39,
                    "K"
                ],
                [
                    161.39,
                    161.42,
                    "G"
                ],
                [
                    161.42,
                    165.21,
                    "AA1"
                ],
                [
                    165.21,
                    171.209932,
                    "T"
                ]
            ]
        }
    }
}